{"_id":{"$oid":"60a136c51e0887da946444ad"},"username":"Stefan91","pwd":"(1234)","email":"stefan91@gmail.com","birth_date":{"$date":"1991-11-02T00:00:00Z"},"favorite_movies":[{"$oid":"60a12e6b1e0887da946444aa"},{"$oid":"60a133711e0887da946444ac"}]}
{"_id":{"$oid":"60a137211e0887da946444ae"},"username":"Leon56","pwd":"(12345)","email":"leon56@gmail.com","birth_date":{"$date":"1991-10-14T00:00:00Z"},"favorite_movies":[{"$oid":"609ff200cda8577ce9cefd57"},{"$oid":"60a130c31e0887da946444ab"}]}
{"_id":{"$oid":"60a1377b1e0887da946444af"},"username":"Cristina90","pwd":"(123456)","email":"cristina90@gmail.com","birth_date":{"$date":"1990-04-25T00:00:00Z"},"favorite_movies":[{"$oid":"60a12d4e1e0887da946444a9"},{"$oid":"60a12e6b1e0887da946444aa"}]}
{"_id":{"$oid":"60a1384c1e0887da946444b1"},"username":"Onisoa97","pwd":"(12345678)","email":"onisoa97@gmail.com","birth_date":{"$date":"1997-02-06T00:00:00Z"},"favorite_movies":[{"$oid":"60a130c31e0887da946444ab"},{"$oid":"60a1267a59d9060f13ba4335"},{"$oid":"60a12b3659d9060f13ba4339"}]}
